{
    "groups": [
      {
        "name": "110",
        "schedule": {
          "week1": {
            "Monday": {
              "subgroup1": [
                {
                  "number": 1,
                  "subject": "Вища математика",
                  "type": "Лекція",
                  "room": "6.200",
                  "teacher": "Томащук О.П."
                },
                {
                  "number": 2,
                  "subject": "Теорія ймовірностей та математична статистика",
                  "type": "Лекція",
                  "room": "6.200",
                  "teacher": "Томащук О.П."
                }
              ],
              "subgroup2": []
            },
            "Tuesday": {
              "subgroup1": [
                {
                  "number": 1,
                  "subject": "Фахова іноземна мова",
                  "type": "Практичне",
                  "room": "8.1301",
                  "teacher": "Денисенко Н.Г."
                },
                {
                  "number": 2,
                  "subject": "Фізичне виховання та самовдосконалення",
                  "type": "Практичне",
                  "room": "Спорт.к.",
                  "teacher": "Фотинюк В.Г."
                }
              ],
              "subgroup2": [
                {
                    "number": 3,
                    "subject": "Фахова іноземна мова",
                    "type": "Практичне",
                    "room": "8.1301",
                    "teacher": "Денисенко Н.Г."
                  }
              ]
            },
            "Wednesday": {
                "subgroup1": [
                {
                        "number": 1,
                        "subject": "Вища математика",
                        "type": "Лекція",
                        "room": "3.108",
                        "teacher": "Гураль В.А"
                 },
                  {
                    "number": 2,
                    "subject": "Теорія ймовірностей та математична статистика",
                    "type": "Лекція",
                    "room": "3.218",
                    "teacher": "Томащук О.П."
                  },
                  {
                    "number": 3,
                    "subject": "Фізика",
                    "type": "Лекція",
                    "room": "1.002",
                    "teacher": "Сакун Т.М."
                  }
                ],
                "subgroup2": [
                ]
              },
              "Thursday": {
                "subgroup1": [
                  {
                        "number": 3,
                        "subject": "Фізика",
                        "type": "Практичне",
                        "room": "1.359",
                        "teacher": "Колісник О.В"
                  },
                  {
                    "number": 4,
                    "subject": "Компютерна графіка та анімація",
                    "type": "Практичне",
                    "room": "6.206",
                    "teacher": "Колісник О.В"
                  }
                ],
                "subgroup2": [
                    {
                        "number": 2,
                        "subject": "Компютерна графіка та анімація",
                        "type": "Практичне",
                        "room": "6.206",
                        "teacher": "Колісник О.В"
                 }
                ]
              },
              "Friday": {
                "subgroup1": [
                  {
                        "number": 1,
                        "subject": "Ділова українська мова",
                        "type": "Лекція",
                        "room": "6. 200",
                        "teacher": "Дячук Т.М"
                  },
                  {
                    "number": 2,
                    "subject": "Компютерна графіка та анімація",
                    "type": "Лекція",
                    "room": "6.200",
                    "teacher": "Колісник О.В"
                  }
                ],
                "subgroup2": [
                 
                ]
              }
          },
          "week2": {
            "Monday": {
              "subgroup1": [
                {
                  "number": 1,
                  "subject": "Вища математика",
                  "type": "Лекція",
                  "room": "6.200",
                  "teacher": "Томащук О.П."
                },
                {
                  "number": 2,
                  "subject": "Теорія ймовірностей та математична статистика",
                  "type": "Лекція",
                  "room": "6.200",
                  "teacher": "Томащук О.П."
                },
                {
                  "number": 3,
                  "subject": "Вища математика",
                  "type": "Практичне",
                  "room": "3.108",
                  "teacher": "Гураль В.А."
                }
              ],
              "subgroup2": []
            },
            "Tuesday": {
                "subgroup1": [
                  {
                    "number": 1,
                    "subject": "Фахова іноземна мова",
                    "type": "Практичне",
                    "room": "8.1301",
                    "teacher": "Денисенко Н.Г."
                  },
                  {
                    "number": 2,
                    "subject": "Фізичне виховання та самовдосконалення",
                    "type": "Практичне",
                    "room": "Спорт.к.",
                    "teacher": "Фотинюк В.Г."
                  }
                ],
                "subgroup2": [
                    
                      {
                        "number": 2,
                        "subject": "Фізичне виховання та самовдосконалення",
                        "type": "Практичне",
                        "room": "Спорт.к.",
                        "teacher": "Фотинюк В.Г."
                      },
                      {
                        "number": 3,
                        "subject": "Фахова іноземна мова",
                        "type": "Практичне",
                        "room": "8.1301",
                        "teacher": "Денисенко Н.Г."
                      }

                ]
              },
              "Wednesday": {
                "subgroup1": [
                  {
                    "number": 1,
                    "subject": "Вища математика",
                    "type": "Практичне",
                    "room": "3.108",
                    "teacher": "Гураль В.А."
                  },
                  {
                    "number": 2,
                    "subject": "Фізика",
                    "type": "Лекція",
                    "room": "1.002",
                    "teacher": "Сакун Т.М."
                  }
                ],
                "subgroup2": []
              },
              
            "Thursday": {
              "subgroup1": [
                {
                  "number": 1,
                  "subject": "Фізика",
                  "type": "Лабораторна",
                  "room": "1.420",
                  "teacher": "Кліщ І.К"
                },
                {
                  "number": 2,
                  "subject": "Компютерна графіка та анімація",
                  "type": "Лабораторна",
                  "room": "6.206",
                  "teacher": "Марінченко Г.Є"
                }
              ],
              "subgroup2": [
                
                {
                    "number": 2,
                    "subject": "Фізика",
                    "type": "Практичне",
                    "room": "1.420",
                    "teacher": "Кліщ І.К"
                  },
                  {
                    "number": 3,
                    "subject": "Компютерна графіка та анімація",
                    "type": "Практичне",
                    "room": "6.206",
                    "teacher": "Колісник О.В"
                  }
              ]
            },
            "Friday": {
              "subgroup1": [
                {
                  "number": 2,
                  "subject": "Компютерна графіка та анімація",
                  "type": "Лекція",
                  "room": "6.200",
                  "teacher": "Колісник О.В"
                },
                {
                  "number": 3,
                  "subject": "Фізика",
                  "type": "Лекція",
                  "room": "1.001",
                  "teacher": "Сакун Т.М."
                }
              ],
              "subgroup2": []
            }
           
          }
        }
      },
      {
        "name": "111",
        "schedule": {
          "week1": {
            "Monday": {
              "subgroup1": [
                {
                  "number": 1,
                  "subject": "Вища математика",
                  "type": "Лекція",
                  "room": "6.200",
                  "teacher": "Томащук О.П."
                },
                {
                  "number": 2,
                  "subject": "Теорія ймовірностей та математична статистика",
                  "type": "Лекція",
                  "room": "6.200",
                  "teacher": "Томащук О.П."
                }, 
                {
                  "number": 3,
                  "subject": "Вища математика",
                  "type": "Практичне",
                  "room": "3.108",
                  "teacher": "Гураль В.А"
                }
              ],
              "subgroup2": []
            },
            "Tuesday": {
              "subgroup1": [
                {
                  "number": 2,
                  "subject": "Фахова іноземна мова",
                  "type": "Практичне",
                  "room": "8.1301",
                  "teacher": "Денисенко Н.Г."
                },
                {
                  "number": 3,
                  "subject": "Фізичне виховання та самовдосконалення",
                  "type": "Практичне",
                  "room": "Спорт.к.",
                  "teacher": "Фотинюк В.Г."
                }
              ],
              "subgroup2": [
                {
                  "number": 3,
                  "subject": "Фахова іноземна мова",
                  "type": "Практичне",
                  "room": "8.1301",
                  "teacher": "Денисенко Н.Г."
                }
              ]
            },
            "Wednesday": {
              "subgroup1": [
                {
                  "number": 2,
                  "subject": "Вища математика",
                  "type": "Практичне",
                  "room": "3.108",
                  "teacher": "Гураль В.А."
                },
                {
                  "number": 3,
                  "subject": "Фізика",
                  "type": "Лекція",
                  "room": "1.002",
                  "teacher": "Сакун Т.М."
                },
                {
                  "number": 3,
                  "subject": "Теорія ймовірностей та математична статистика",
                  "type": "Практичне",
                  "room": "3.218",
                  "teacher": "Томащук О.П."
                }
              ],
              "subgroup2": []
            },
            "Thursday": {
              "subgroup1": [
                {
                  "number": 3,
                  "subject": "Компютерна графіка та анімація",
                  "type": "Практичне",
                  "room": "6.206",
                  "teacher": "Колісник О.В"
                },
                {
                  "number": 3,
                  "subject": "Фізика",
                  "type": "Практичне",
                  "room": "1.359",
                  "teacher": "Марінченко Г.Є"
                }
              ],
              "subgroup2": [
                {
                  "number": 3,
                  "subject": "Компютерна графіка та анімація",
                  "type": "Практичне",
                  "room": "6.206",
                  "teacher": "Колісник О.В"
                }
              ]
            },
            "Friday": {
              "subgroup1": [
                {
                  "number": 1,
                  "subject": "Ділова українська мова",
                  "type": "Лекція",
                  "room": "6.200",
                  "teacher": "Дячук Т.М"
                },
                {
                  "number": 2,
                  "subject": "Компютерна графіка та анімація",
                  "type": "Лекція",
                  "room": "6.200",
                  "teacher": "Колісник О.В"
                }
              ],
              "subgroup2": [
               
              ]
            }
          },
          "week2": {
            "Monday": {
              "subgroup1": [
                {
                  "number": 1,
                  "subject": "Вища математика",
                  "type": "Лекція",
                  "room": "6.200",
                  "teacher": "Томащук О.П."
                },
                {
                  "number": 2,
                  "subject": "Теорія ймовірностей та математична статистика",
                  "type": "Лекція",
                  "room": "6.200",
                  "teacher": "Томащук О.П."
                }
              ],
              "subgroup2": []
            },
            "Tuesday": {
              "subgroup1": [
                {
                  "number": 2,
                  "subject": "Фахова іноземна мова",
                  "type": "Практичне",
                  "room": "8.1301",
                  "teacher": "Денисенко Н.Г."
                },
                {
                  "number": 3,
                  "subject": "Фізичне виховання та самовдосконалення",
                  "type": "Практичне",
                  "room": "Спорт.к.",
                  "teacher": "Фотинюк В.Г."
                }
              ],
              "subgroup2": [
                {
                  "number": 4,
                  "subject": "Фахова іноземна мова",
                  "type": "Практичне",
                  "room": "8.1301",
                  "teacher": "Денисенко Н.Г."
                }
              ]
            },
            "Wednesday": {
              "subgroup1": [
                {
                  "number": 2,
                  "subject": "Вища математика",
                  "type": "Практичне",
                  "room": "3.108",
                  "teacher": "Гураль В.А."
                },
                {
                  "number": 3,
                  "subject": "Ділова українська мова",
                  "type": "Практичне",
                  "room": "10.218",
                  "teacher": "Дячук Т.М."
                }
              ],
              "subgroup2": []
            },
            "Thursday": {
              "subgroup1": [
                {
                  "number": 3,
                  "subject": "Фізика",
                  "type": "Лабораторна",
                  "room": "1.420",
                  "teacher": "Кліщ І.К"
                },
                {
                  "number": 4,
                  "subject": "Компютерна графіка та анімація",
                  "type": "Лабораторна",
                  "room": "6.206",
                  "teacher": "Колісник О.В"
                }
              ],
              "subgroup2": [
                {
                  "number": 4,
                  "subject": "Фізика",
                  "type": "Лабораторна",
                  "room": "1.420",
                  "teacher": "Кліщ І.К"
                },
                {
                  "number": 5,
                  "subject": "Компютерна графіка та анімація",
                  "type": "Лабораторна",
                  "room": "6.206",
                  "teacher": "Колісник О.В"
                }
              ]
            },
            "Friday": {
              "subgroup1": [
                {
                  "number": 2,
                  "subject": "Компютерна графіка та анімація",
                  "type": "Лекція",
                  "room": "6.200",
                  "teacher": "Колісник О.В"
                },
                {
                  "number": 3,
                  "subject": "Фізика",
                  "type": "Лекція",
                  "room": "1.001",
                  "teacher": "Сакун Т.М."
                }
              ],
              "subgroup2": []
            }
          }
        }
      },
      {
        "name": "112",
        "schedule": {
          "week1": {
            "Monday": {
              "subgroup1": [
                {
                  "number": 1,
                  "subject": "Вища математика",
                  "type": "Лекція",
                  "room": "6.200",
                  "teacher": "Томащук О.П."
                },
                {
                  "number": 2,
                  "subject": "Теорія ймовірностей та математична статистика",
                  "type": "Лекція",
                  "room": "6.200",
                  "teacher": "Томащук О.П."
                }
              ],
              "subgroup2": []
            },
            "Tuesday": {
              "subgroup1": [
                {
                  "number": 2,
                  "subject": "Вища математика",
                  "type": "Практичне",
                  "room": "3.108",
                  "teacher": "Гураль В.А."
                },
                {
                  "number": 3,
                  "subject": "Фізика",
                  "type": "Практичне",
                  "room": "1.357",
                  "teacher": "Сакун Т.М."
                }
              ],
              "subgroup2": []
            },
            "Wednesday": {
              "subgroup1": [
                {
                  "number": 2,
                  "subject": "Фізика",
                  "type": "Лекція",
                  "room": "1.002",
                  "teacher": "Сакун Т.М."
                },
                {
                  "number": 3,
                  "subject": "Компютерна графіка та анімація",
                  "type": "Практичне",
                  "room": "6.206",
                  "teacher": "Колісник О.В"
                }
              ],
              "subgroup2": []
            },
            "Thursday": {
              "subgroup1": [
                {
                  "number": 1,
                  "subject": "Вища математика",
                  "type": "Практичне",
                  "room": "3.108",
                  "teacher": "Гураль В.А"
                },
                {
                  "number": 2,
                  "subject": "Фізичне виховання та самовдосконалення",
                  "type": "Практичне",
                  "room": "Спорт.к.",
                  "teacher": "Фотинюк В.Г."
                },
                {
                  "number": 3,
                  "subject": "Фахова іноземна мова",
                  "type": "Практичне",
                  "room": "3.211",
                  "teacher": "Сорокун Г.В."
                }
              ],
              "subgroup2": []
            },
            "Friday": {
              "subgroup1": [
                {
                  "number": 1,
                  "subject": "Ділова українська мова",
                  "type": "Лекція",
                  "room": "6.200",
                  "teacher": "Дячук Т.М"
                },
                {
                  "number": 2,
                  "subject": "Компютерна графіка та анімація",
                  "type": "Лекція",
                  "room": "6.20",
                  "teacher": "Колісник О.В"
                }
              ],
              "subgroup2": []
            }
          },
          "week2": {
            "Monday": {
              "subgroup1": [
                {
                  "number": 1,
                  "subject": "Вища математика",
                  "type": "Лекція",
                  "room": "6.200",
                  "teacher": "Томащук О.П."
                },
                {
                  "number": 2,
                  "subject": "Теорія ймовірностей та математична статистика",
                  "type": "Лекція",
                  "room": "6.200",
                  "teacher": "Томащук О.П."
                }
              ],
              "subgroup2": []
            },
            "Tuesday": {
              "subgroup1": [
                {
                  "number": 1,
                  "subject": "Фізика",
                  "type": "Лабораторна",
                  "room": "1.420",
                  "teacher": "Сакун Т.М."
                },
                {
                  "number": 2,
                  "subject": "Теорія ймовірностей та математична статистика",
                  "type": "Практичне",
                  "room": "3.218",
                  "teacher": "Томащук О.П."
                }
              ],
              "subgroup2": []
            },
            "Wednesday": {
              "subgroup1": [
                {
                  "number": 3,
                  "subject": "Фахова іноземна мова",
                  "type": "Практичне",
                  "room": "3.211",
                  "teacher": "Сорокун Г.В."
                },
                {
                  "number": 4,
                  "subject": "Ділова українська мова",
                  "type": "Практичне",
                  "room": "10.218",
                  "teacher": "Дячук Т.М"
                },
                {
                  "number": 5,
                  "subject": "Ділова українська мова",
                  "type": "Практичне",
                  "room": "10.218",
                  "teacher": "Дячук Т.М"
                }
              ],
              "subgroup2": []
            },
            "Thursday": {
              "subgroup1": [
                {
                  "number": 1,
                  "subject": "Вища математика",
                  "type": "Практичне",
                  "room": "3.108",
                  "teacher": "Гураль В.А"
                },
                {
                  "number": 2,
                  "subject": "Фізичне виховання та самовдосконалення",
                  "type": "Практичне",
                  "room": "Спорт.к.",
                  "teacher": "Фотинюк В.Г."
                }
              ],
              "subgroup2": []
            },
            "Friday": {
              "subgroup1": [
                {
                  "number": 2,
                  "subject": "Компютерна графіка та анімація",
                  "type": "Лекція",
                  "room": "6.200",
                  "teacher": "Колісник О.В"
                },
                {
                  "number": 3,
                  "subject": "Фізика",
                  "type": "Лекція",
                  "room": "1.001",
                  "teacher": "Сакун Т.М."
                }
              ],
              "subgroup2": []
            }
          }
        }
      }
    ]
  }
  